[{"record":{"RecordNumber":1,"Allergen":"none","appointment":null,"timeOfAppointment":"0001-01-01T00:00:00","anamnesis":null,"doctorsName":null,"patientsUsername":null},"isPatientBaned":{"isBaned":false,"ActivitiyCounter":0,"TimeOfActivities":[]},"id":1,"Username":"pera123","Password":"kgbpassword","firstName":"Pera","lastName":"Peric","Jmbg":"020202455555","EMail":null,"PhoneNumber":"064-889-554","DateOfBirth":"0001-01-01T00:00:00","Rool":0},{"record":{"RecordNumber":2,"Allergen":"none","appointment":null,"timeOfAppointment":"0001-01-01T00:00:00","anamnesis":null,"doctorsName":null,"patientsUsername":null},"isPatientBaned":{"isBaned":false,"ActivitiyCounter":6,"TimeOfActivities":["2021-06-03T19:14:54.4035072+02:00","2021-06-03T19:15:06.4733542+02:00","2021-06-06T14:05:45.5115281+02:00","2021-06-06T17:42:27.7268893+02:00","2021-06-06T17:44:26.6020546+02:00","2021-06-07T13:44:58.6338937+02:00"]},"id":2,"Username":"aca","Password":"222","firstName":"Aleksa","lastName":"Kralj","Jmbg":"00000022323","EMail":"aaca@gmail.com","PhoneNumber":"0232323","DateOfBirth":"0001-01-01T00:00:00","Rool":0},{"record":{"RecordNumber":3,"Allergen":"none","appointment":null,"timeOfAppointment":"0001-01-01T00:00:00","anamnesis":null,"doctorsName":null,"patientsUsername":null},"isPatientBaned":{"isBaned":false,"ActivitiyCounter":0,"TimeOfActivities":[]},"id":5,"Username":null,"Password":null,"firstName":"Nikolina","lastName":"Todic","Jmbg":null,"EMail":null,"PhoneNumber":null,"DateOfBirth":"0001-01-01T00:00:00","Rool":0},{"record":{"RecordNumber":4,"Allergen":"brufen","appointment":null,"timeOfAppointment":"0001-01-01T00:00:00","anamnesis":null,"doctorsName":null,"patientsUsername":null},"isPatientBaned":{"isBaned":false,"ActivitiyCounter":0,"TimeOfActivities":[]},"id":3,"Username":null,"Password":null,"firstName":"Anamarija","lastName":"Popovic","Jmbg":null,"EMail":null,"PhoneNumber":null,"DateOfBirth":"0001-01-01T00:00:00","Rool":0},{"record":{"RecordNumber":5,"Allergen":"paracetamol","appointment":null,"timeOfAppointment":"0001-01-01T00:00:00","anamnesis":null,"doctorsName":null,"patientsUsername":null},"isPatientBaned":{"isBaned":false,"ActivitiyCounter":0,"TimeOfActivities":[]},"id":4,"Username":null,"Password":null,"firstName":"Mirko","lastName":"Mirkovic","Jmbg":null,"EMail":null,"PhoneNumber":null,"DateOfBirth":"0001-01-01T00:00:00","Rool":0}]