[
  {
    "Id": "1",
    "Name": "Notifikacija1",
    "Date": "2021-04-21T19:00:00",
    "Description": "Opis1",
  },
  {
    "Id": "2",
    "Name": "Notifikacija2",
    "Date": "2021-04-22T19:00:00",
    "Description": "Opis2"
  },
  {
    "Id": "3",
    "Name": "Notifikacija3",
    "Date": "2021-04-20T19:00:00",
    "Description": "Opis2"
  },
  {
    "Id": "4",
    "Name": "Notifikacija4",
    "Date": "2021-04-21T16:00:00",
    "Description": "Opis4"
  }
  ,
  {
    "Id": "5",
    "Name": "Notifikacija5",
    "Date": "2021-04-20T19:22:00",
    "Description": "Opis5"
  },
  {
    "Id": "6",
    "Name": "Notifikacija6",
    "Date": "2021-04-20T19:57:00",
    "Description": "Opis5"
  }

]
